nene/__init__.py
nene/_api.py
nene/_version.py
nene/_version_generated.py
nene/cli.py
nene/crawling.py
nene/parsing.py
nene/printing.py
nene/rendering.py
nene/utils.py
nene-0.10.0.dist-info/licenses/LICENSE.txt
nene-0.10.0.dist-info/METADATA
nene-0.10.0.dist-info/WHEEL
nene-0.10.0.dist-info/entry_points.txt
nene-0.10.0.dist-info/top_level.txt
nene-0.10.0.dist-info/zip-safe
nene-0.10.0.dist-info/RECORD
