Metadata-Version: 2.4
Name: nene
Version: 0.10.0
Summary: A no-frills static site generator
Home-page: https://nene.leouieda.com
Author: Leonardo Uieda
Author-email: leo@uieda.com
License: MIT
Project-URL: Documentation, https://nene.leouieda.com
Project-URL: Release Notes, https://github.com/leouieda/nene/releases
Project-URL: Bug Tracker, https://github.com/leouieda/nene/issues
Project-URL: Source Code, https://github.com/leouieda/nene
Keywords: html,markdown
Platform: any
Classifier: Development Status :: 4 - Beta
Classifier: Intended Audience :: Developers
Classifier: License :: OSI Approved :: MIT License
Classifier: Natural Language :: English
Classifier: Operating System :: OS Independent
Classifier: Topic :: Text Processing :: Markup :: HTML
Classifier: Topic :: Text Processing :: Markup :: Markdown
Classifier: Programming Language :: Python :: 3 :: Only
Requires-Python: >=3.9
License-File: LICENSE.txt
Requires-Dist: markdown-it-py>=2.0
Requires-Dist: mdit-py-plugins>=0.3
Requires-Dist: jinja2>=3.0
Requires-Dist: pyyaml>=6.0
Requires-Dist: livereload>=2.6
Requires-Dist: click>=8
Requires-Dist: rich>=10.9
Requires-Dist: pygments>=2.17
Provides-Extra: jupyter
Requires-Dist: nbformat; extra == "jupyter"
Requires-Dist: nbconvert; extra == "jupyter"
Dynamic: license-file
